TutorialspointApexJiaocheng/README.md
TutorialspointApexJiaocheng/__init__.py
TutorialspointApexJiaocheng/__main__.py
TutorialspointApexJiaocheng/file.epub
TutorialspointApexJiaocheng/index.html
TutorialspointApexJiaocheng/css/__init__.py
TutorialspointApexJiaocheng/css/annotations.css
TutorialspointApexJiaocheng/css/main.css
TutorialspointApexJiaocheng/css/normalize.css
TutorialspointApexJiaocheng/css/popup.css
TutorialspointApexJiaocheng/font/__init__.py
TutorialspointApexJiaocheng/font/fontello.eot
TutorialspointApexJiaocheng/font/fontello.svg
TutorialspointApexJiaocheng/font/fontello.ttf
TutorialspointApexJiaocheng/font/fontello.woff
TutorialspointApexJiaocheng/img/__init__.py
TutorialspointApexJiaocheng/img/annotator-glyph-sprite.png
TutorialspointApexJiaocheng/img/annotator-icon-sprite.png
TutorialspointApexJiaocheng/img/apple-touch-icon.png
TutorialspointApexJiaocheng/img/cancelfullscreen.png
TutorialspointApexJiaocheng/img/close.png
TutorialspointApexJiaocheng/img/fullscreen.png
TutorialspointApexJiaocheng/img/loader.gif
TutorialspointApexJiaocheng/img/menu-icon.png
TutorialspointApexJiaocheng/img/save.png
TutorialspointApexJiaocheng/img/saved.png
TutorialspointApexJiaocheng/img/settings-s.png
TutorialspointApexJiaocheng/img/settings.png
TutorialspointApexJiaocheng/img/star.png
TutorialspointApexJiaocheng/js/__init__.py
TutorialspointApexJiaocheng/js/epub.js
TutorialspointApexJiaocheng/js/epub.min.js
TutorialspointApexJiaocheng/js/epub.min.map
TutorialspointApexJiaocheng/js/hooks.min.js
TutorialspointApexJiaocheng/js/hooks.min.map
TutorialspointApexJiaocheng/js/reader.js
TutorialspointApexJiaocheng/js/reader.js.map
TutorialspointApexJiaocheng/js/reader.min.js
TutorialspointApexJiaocheng/js/reader.min.map
TutorialspointApexJiaocheng/js/hooks/__init__.py
TutorialspointApexJiaocheng/js/hooks/extensions/__init__.py
TutorialspointApexJiaocheng/js/hooks/extensions/highlight.js
TutorialspointApexJiaocheng/js/libs/__init__.py
tutorialspoint_apex_jiaocheng-2024.3.2.0.dist-info/METADATA
tutorialspoint_apex_jiaocheng-2024.3.2.0.dist-info/WHEEL
tutorialspoint_apex_jiaocheng-2024.3.2.0.dist-info/entry_points.txt
tutorialspoint_apex_jiaocheng-2024.3.2.0.dist-info/top_level.txt
tutorialspoint_apex_jiaocheng-2024.3.2.0.dist-info/RECORD
